pyftools/__init__.py
pyftools/factor.py
pyftools/fcollapse.py
pyftools/ftools.py
pyftools_stata-0.2.0.dist-info/licenses/LICENSE
pyftools_stata-0.2.0.dist-info/METADATA
pyftools_stata-0.2.0.dist-info/WHEEL
pyftools_stata-0.2.0.dist-info/top_level.txt
pyftools_stata-0.2.0.dist-info/RECORD
