Metadata-Version: 2.4
Name: pyftools-stata
Version: 0.2.0
Summary: Python implementation of Stata's ftools - Fast data manipulation tools
Author-email: Bryce Wang <brycew6m@stanford.edu>, Collin Liu <junnebailiu@gmail.com>
Maintainer-email: Bryce Wang <brycew6m@stanford.edu>
License-Expression: MIT
Project-URL: Homepage, https://github.com/brycewang-stanford/pyftools
Project-URL: Documentation, https://github.com/brycewang-stanford/pyftools
Project-URL: Repository, https://github.com/brycewang-stanford/pyftools
Project-URL: Bug Tracker, https://github.com/brycewang-stanford/pyftools/issues
Project-URL: Changelog, https://github.com/brycewang-stanford/pyftools/releases
Keywords: data manipulation,categorical variables,stata,ftools,statistics
Classifier: Development Status :: 4 - Beta
Classifier: Intended Audience :: Developers
Classifier: Intended Audience :: Science/Research
Classifier: Topic :: Scientific/Engineering
Classifier: Topic :: Software Development :: Libraries :: Python Modules
Classifier: Programming Language :: Python :: 3
Classifier: Programming Language :: Python :: 3.8
Classifier: Programming Language :: Python :: 3.9
Classifier: Programming Language :: Python :: 3.10
Classifier: Programming Language :: Python :: 3.11
Classifier: Programming Language :: Python :: 3.12
Classifier: Programming Language :: Python :: 3.13
Classifier: Operating System :: OS Independent
Requires-Python: >=3.8
License-File: LICENSE
Requires-Dist: numpy>=1.19.0
Requires-Dist: pandas>=1.3.0
Provides-Extra: dev
Requires-Dist: pytest>=6.0; extra == "dev"
Requires-Dist: pytest-cov; extra == "dev"
Requires-Dist: black; extra == "dev"
Requires-Dist: flake8; extra == "dev"
Requires-Dist: mypy; extra == "dev"
Requires-Dist: sphinx; extra == "dev"
Requires-Dist: sphinx-rtd-theme; extra == "dev"
Requires-Dist: build; extra == "dev"
Requires-Dist: twine; extra == "dev"
Provides-Extra: test
Requires-Dist: pytest>=6.0; extra == "test"
Requires-Dist: pytest-cov; extra == "test"
Dynamic: license-file
